zseeker/__init__.py
zseeker/constants.py
zseeker/zdna_calculator.py
zseeker/zseeker.py
ZSeeker-1.8.dist-info/LICENSE.md
ZSeeker-1.8.dist-info/METADATA
ZSeeker-1.8.dist-info/WHEEL
ZSeeker-1.8.dist-info/entry_points.txt
ZSeeker-1.8.dist-info/top_level.txt
ZSeeker-1.8.dist-info/RECORD
