Metadata-Version: 2.2
Name: ZSeeker
Version: 1.8
Summary: ZSeeker is a cli tool to find the propensity of B-DNA to form Z-DNA structures. 
Home-page: https://github.com/Georgakopoulos-Soares-lab/ZSeeker
Author: Nikol Chantzi, Patsakis Michail , Provatas Kimon, Ilias Georgakopoulos Soares, Ioannis Mouratidis
Author-email: kap6605@psu.edu , mpp5977@psu.edu
Classifier: Programming Language :: Python :: 3
Classifier: License :: OSI Approved :: GNU General Public License v3 (GPLv3)
Classifier: Operating System :: OS Independent
Requires-Python: >=3.10
License-File: LICENSE.md
Requires-Dist: biopython
Requires-Dist: argparse
Requires-Dist: pathlib
Requires-Dist: termcolor
Requires-Dist: numpy
Requires-Dist: scipy
Requires-Dist: pandas
Requires-Dist: streamlit
Requires-Dist: text-highlighter
Requires-Dist: plotly
Requires-Dist: altair==4.0
Requires-Dist: matplotlib
Dynamic: author
Dynamic: author-email
Dynamic: classifier
Dynamic: description
Dynamic: description-content-type
Dynamic: home-page
Dynamic: requires-dist
Dynamic: requires-python
Dynamic: summary
